flask_via
tests
