Metadata-Version: 1.1
Name: Flask-Via
Version: 2014.05.19.2
Summary: Provides a clean, simple URL routing framework for growing Flask Applications.
Home-page: http://flask-via.soon.build
Author: Chris Reeves
Author-email: hello@chris.reeves.io
License: MIT
Keywords: Flask,Routing,Routes,URLs,Views
Platform: UNKNOWN
Classifier: Framework :: Flask
Classifier: Environment :: Web Environment
Classifier: Intended Audience :: Developers
Classifier: License :: OSI Approved :: MIT License
Classifier: Development Status :: 5 - Production/Stable
Classifier: Operating System :: OS Independent
Classifier: Programming Language :: Python
Classifier: Programming Language :: Python :: 2
Classifier: Programming Language :: Python :: 2.7
Classifier: Programming Language :: Python :: 3
Classifier: Programming Language :: Python :: 3.3
Classifier: Programming Language :: Python :: 3.4
Classifier: Topic :: Software Development
Classifier: Topic :: Software Development :: Libraries :: Python Modules
Classifier: Topic :: Internet :: WWW/HTTP :: Dynamic Content
